binance_sdk_convert/__init__.py
binance_sdk_convert/convert.py
binance_sdk_convert/metadata.py
binance_sdk_convert/rest_api/__init__.py
binance_sdk_convert/rest_api/api/__init__.py
binance_sdk_convert/rest_api/api/market_data_api.py
binance_sdk_convert/rest_api/api/trade_api.py
binance_sdk_convert/rest_api/models/__init__.py
binance_sdk_convert/rest_api/models/accept_quote_response.py
binance_sdk_convert/rest_api/models/cancel_limit_order_response.py
binance_sdk_convert/rest_api/models/enums.py
binance_sdk_convert/rest_api/models/get_convert_trade_history_response.py
binance_sdk_convert/rest_api/models/get_convert_trade_history_response_list_inner.py
binance_sdk_convert/rest_api/models/list_all_convert_pairs_response.py
binance_sdk_convert/rest_api/models/list_all_convert_pairs_response_inner.py
binance_sdk_convert/rest_api/models/order_status_response.py
binance_sdk_convert/rest_api/models/place_limit_order_response.py
binance_sdk_convert/rest_api/models/query_limit_open_orders_response.py
binance_sdk_convert/rest_api/models/query_limit_open_orders_response_list_inner.py
binance_sdk_convert/rest_api/models/query_order_quantity_precision_per_asset_response.py
binance_sdk_convert/rest_api/models/query_order_quantity_precision_per_asset_response_inner.py
binance_sdk_convert/rest_api/models/send_quote_request_response.py
binance_sdk_convert/rest_api/rest_api.py
binance_sdk_convert-3.2.0.dist-info/METADATA
binance_sdk_convert-3.2.0.dist-info/WHEEL
binance_sdk_convert-3.2.0.dist-info/licenses/LICENCE
binance_sdk_convert-3.2.0.dist-info/RECORD
